epm240/ALTUFM/counter.v
module counter ( input clk,  output  reg  led );

    parameter PERIODLED=2;
//altumf_osc osc(.oscena(1'b1),.osc(clk));
    integer count=0;
    always @ (posedge clk)	begin
	if (count<=PERIODLED) begin                          
	    led<=0;
	    count=count+1;
	  end                          
	else if (count>=PERIODLED && count<=PERIODLED*2)
	  begin
	    led<=1;
	    count=count+1;
	  end else count=0;
	end              
endmodule

epm240/ALTUFM/tcounter.v
`timescale 1ms/ 1 ms
module test_counter();

reg clk;
wire led;

//устанавливаем экземпляр тестируемого модуля
counter counter_inst( clk, led );
//моделируем сигнал тактовой частоты
always
  #10 clk = ~clk;
//от начала времени...
initial
begin
  clk = 0;
  //пауза длительностью "50"
  #50  $display("Running---");
end 

//заканчиваем симуляцию в момент времени "400"
initial
begin
  #400 $finish;
end

//создаем файл VCD для последующего анализа сигналов
initial
begin
  $dumpfile("out.vcd");
  $dumpvars(0,test_counter);
end

//наблюдаем на некоторыми сигналами системы
initial
$monitor($stime,,  clk,,, led );

endmodule

epm240/ALTUFM/out.vcd
$date
	Fri Apr 19 20:24:48 2024
$end
$version
	Icarus Verilog
$end
$timescale
	1ms
$end
$scope module test_counter $end
$var wire 1 ! led $end
$var reg 1 " clk $end
$scope module counter_inst $end
$var wire 1 " clk $end
$var reg 1 ! led $end
$var integer 32 # count [31:0] $end
$upscope $end
$upscope $end
$enddefinitions $end
#0
$dumpvars
b0 #
0"
x!
$end
#10
0!
b1 #
1"
#20
0"
#30
b10 #
1"
#40
0"
#50
b11 #
1"
#60
0"
#70
1!
b100 #
1"
#80
0"
#90
b101 #
1"
#100
0"
#110
b0 #
1"
#120
0"
#130
0!
b1 #
1"
#140
0"
#150
b10 #
1"
#160
0"
#170
b11 #
1"
#180
0"
#190
1!
b100 #
1"
#200
0"
#210
b101 #
1"
#220
0"
#230
b0 #
1"
#240
0"
#250
0!
b1 #
1"
#260
0"
#270
b10 #
1"
#280
0"
#290
b11 #
1"
#300
0"
#310
1!
b100 #
1"
#320
0"
#330
b101 #
1"
#340
0"
#350
b0 #
1"
#360
0"
#370
0!
b1 #
1"
#380
0"
#390
b10 #
1"
