epm240/ALTUFM/counter.v
module counter ( input clk,  output  reg  led1, output reg led2 );

    parameter PERIODLED=2;
              //altumf_osc osc(.oscena(1'b1),.osc(clk));
    integer countone=0; // Счетчик одноразовый
    integer count=0;    // Счетчик периодичный
    always @ (posedge clk)	
      begin
	// Вариант непосредственного указания
	if (countone<5)      led1<=0;
	if (countone>=5 && countone<10)     led1<=1;
	else led1<=0;
	countone=countone+1;

	// Вариант периодичности
	if (count<=PERIODLED) 
	   begin                          
	    led2<=0;
	    count=count+1;
	  end                          
	else if (count>=PERIODLED && count<=PERIODLED*2)
	   begin
	    led2<=1;
	    count=count+1;
	   end 
         else count=0;
    end              
endmodule

epm240/ALTUFM/tcounter.v
`timescale 1ms/ 1 ms
module test_counter();

reg clk;
wire led1, led2;

//устанавливаем экземпляр тестируемого модуля
counter counter_inst( clk, led1, led2 );
//моделируем сигнал тактовой частоты
always
  #10  clk = ~clk;

//от начала времени...
initial
begin
  clk = 0;
  //пауза длительностью "50"
  #50  $display("Running---%d",$time);
       //$monitor(led);        
end 

//заканчиваем симуляцию в момент времени "400"
initial
begin
  #400 $finish;
end

//создаем файл VCD для последующего анализа сигналов
initial
begin
  $dumpfile("out.vcd");
  $dumpvars(0,test_counter);
end

//наблюдаем на некоторыми сигналами системы
initial
$monitor($stime,,,  clk,,, led1,,, led2 );

endmodule

epm240/ALTUFM/out.vcd
$date
	Sun Apr 21 18:33:31 2024
$end
$version
	Icarus Verilog
$end
$timescale
	1ms
$end
$scope module test_counter $end
$var wire 1 ! led2 $end
$var wire 1 " led1 $end
$var reg 1 # clk $end
$scope module counter_inst $end
$var wire 1 # clk $end
$var reg 1 " led1 $end
$var reg 1 ! led2 $end
$var integer 32 $ count [31:0] $end
$var integer 32 % countone [31:0] $end
$upscope $end
$upscope $end
$enddefinitions $end
#0
$dumpvars
b0 %
b0 $
0#
x"
x!
$end
#10
0!
0"
b1 $
b1 %
1#
#20
0#
#30
b10 $
b10 %
1#
#40
0#
#50
b11 $
b11 %
1#
#60
0#
#70
1!
b100 $
b100 %
1#
#80
0#
#90
b101 $
b101 %
1#
#100
0#
#110
1"
b0 $
b110 %
1#
#120
0#
#130
0!
b1 $
b111 %
1#
#140
0#
#150
b10 $
b1000 %
1#
#160
0#
#170
b11 $
b1001 %
1#
#180
0#
#190
1!
b100 $
b1010 %
1#
#200
0#
#210
0"
b101 $
b1011 %
1#
#220
0#
#230
b0 $
b1100 %
1#
#240
0#
#250
0!
b1 $
b1101 %
1#
#260
0#
#270
b10 $
b1110 %
1#
#280
0#
#290
b11 $
b1111 %
1#
#300
0#
#310
1!
b100 $
b10000 %
1#
#320
0#
#330
b101 $
b10001 %
1#
#340
0#
#350
b0 $
b10010 %
1#
#360
0#
#370
0!
b1 $
b10011 %
1#
#380
0#
#390
b10 $
b10100 %
1#
